odoo8_addon_crm_location-8.0.1.0.0.99.dev19-py3.8-nspkg.pth
odoo_addons/crm_location/README.rst
odoo_addons/crm_location/__init__.py
odoo_addons/crm_location/__openerp__.py
odoo_addons/crm_location/i18n/bg.po
odoo_addons/crm_location/i18n/ca.po
odoo_addons/crm_location/i18n/crm_location.pot
odoo_addons/crm_location/i18n/de.po
odoo_addons/crm_location/i18n/es.po
odoo_addons/crm_location/i18n/es_ES.po
odoo_addons/crm_location/i18n/fi.po
odoo_addons/crm_location/i18n/fr.po
odoo_addons/crm_location/i18n/hr.po
odoo_addons/crm_location/i18n/it.po
odoo_addons/crm_location/i18n/nl_NL.po
odoo_addons/crm_location/i18n/pt_BR.po
odoo_addons/crm_location/i18n/sk.po
odoo_addons/crm_location/i18n/sl.po
odoo_addons/crm_location/i18n/tr_TR.po
odoo_addons/crm_location/i18n/zh_CN.po
odoo_addons/crm_location/models/__init__.py
odoo_addons/crm_location/models/crm_lead.py
odoo_addons/crm_location/static/description/icon.png
odoo_addons/crm_location/views/crm_lead_view.xml
odoo8_addon_crm_location-8.0.1.0.0.99.dev19.dist-info/METADATA
odoo8_addon_crm_location-8.0.1.0.0.99.dev19.dist-info/WHEEL
odoo8_addon_crm_location-8.0.1.0.0.99.dev19.dist-info/namespace_packages.txt
odoo8_addon_crm_location-8.0.1.0.0.99.dev19.dist-info/top_level.txt
odoo8_addon_crm_location-8.0.1.0.0.99.dev19.dist-info/RECORD
